gpts/__init__.py
gpts/models.py
gpts-0.0.8.dist-info/METADATA
gpts-0.0.8.dist-info/WHEEL
gpts-0.0.8.dist-info/top_level.txt
gpts-0.0.8.dist-info/RECORD
