Metadata-Version: 2.1
Name: gpts
Version: 0.0.8
Summary: Unix language driver for software 2.0
Author-email: Ramya Kottapalli <rskottap@gmail.com>, Jason Wilkes <notarealdeveloper@gmail.com>
Project-URL: source, https://github.com/notarealdeveloper/gpts
Project-URL: download, https://pypi.org/project/gpts/#files
Requires-Dist: llama-cpp-python
Requires-Dist: transformers
Requires-Dist: accelerate
Requires-Dist: guidance
Requires-Dist: minml
Provides-Extra: develop
Requires-Dist: build ; extra == 'develop'
Requires-Dist: pytest ; extra == 'develop'
